scraping/__init__.py
scraping/proxy.py
scraping/scraper.py
scrape_html-0.0.24.dist-info/LICENSE
scrape_html-0.0.24.dist-info/METADATA
scrape_html-0.0.24.dist-info/WHEEL
scrape_html-0.0.24.dist-info/top_level.txt
scrape_html-0.0.24.dist-info/RECORD
