Metadata-Version: 2.1
Name: scrape-html
Version: 0.0.24
Summary: Get html in string from a page
Home-page: https://github.com/AndyPythonCode/scrape-html
Author: Andy J. Arciniega
Author-email: andyarciniegas24@gmail.com
License: UNKNOWN
Platform: UNKNOWN
Classifier: Programming Language :: Python :: 3
Classifier: License :: OSI Approved :: MIT License
Classifier: Operating System :: OS Independent
Requires-Python: >=3.7
License-File: LICENSE
Requires-Dist: pydantic
Requires-Dist: selenium
